cone.sql-0.8-py3.9-nspkg.pth
cone/sql/__init__.py
cone/sql/acl.py
cone/sql/model.py
cone/sql/testing.py
cone/sql/ugm.py
cone/sql/tests/__init__.py
cone/sql/tests/test_acl.py
cone/sql/tests/test_cone_ugm.py
cone/sql/tests/test_model.py
cone/sql/tests/test_sql.py
cone/sql/tests/test_ugm.py
cone.sql-0.8.dist-info/LICENSE.rst
cone.sql-0.8.dist-info/METADATA
cone.sql-0.8.dist-info/WHEEL
cone.sql-0.8.dist-info/entry_points.txt
cone.sql-0.8.dist-info/namespace_packages.txt
cone.sql-0.8.dist-info/top_level.txt
cone.sql-0.8.dist-info/RECORD
