Metadata-Version: 2.1
Name: cone.sql
Version: 0.8
Summary: SQLAlchemy integration for cone.app
Home-page: http://github.com/conestack/cone.sql
Author: Cone Contributors
Author-email: dev@conestack.org
License: Simplified BSD
Keywords: node pyramid cone web
Classifier: Environment :: Web Environment
Classifier: Programming Language :: Python
Classifier: Topic :: Internet :: WWW/HTTP :: Dynamic Content
License-File: LICENSE.rst
Requires-Dist: cone.app >=1.0.3
Requires-Dist: node.ext.ugm >=0.9.13
Requires-Dist: pyramid-retry
Requires-Dist: pyramid-tm
Requires-Dist: setuptools
Requires-Dist: zope.sqlalchemy
Provides-Extra: test
Requires-Dist: zope.testrunner ; extra == 'test'
Requires-Dist: cone.ugm ; extra == 'test'
Provides-Extra: ugm
Requires-Dist: cone.ugm ; extra == 'ugm'
